neurodocker/__init__.py
neurodocker/_version.py
neurodocker/cli/__init__.py
neurodocker/cli/cli.py
neurodocker/cli/generate.py
neurodocker/cli/minify/__init__.py
neurodocker/cli/minify/_prune.py
neurodocker/cli/minify/_trace.sh
neurodocker/cli/minify/trace.py
neurodocker/cli/minify/tests/test_minify.py
neurodocker/cli/tests/sample-template-jq.yaml
neurodocker/cli/tests/test_build_images_with_cli.py
neurodocker/cli/tests/test_cli.py
neurodocker/reproenv/__init__.py
neurodocker/reproenv/exceptions.py
neurodocker/reproenv/renderers.py
neurodocker/reproenv/state.py
neurodocker/reproenv/template.py
neurodocker/reproenv/types.py
neurodocker/reproenv/schemas/renderer.json
neurodocker/reproenv/schemas/template.json
neurodocker/reproenv/tests/__init__.py
neurodocker/reproenv/tests/sample-template-jq.yaml
neurodocker/reproenv/tests/test_build_images_from_registered_templates.py
neurodocker/reproenv/tests/test_build_images_simple.py
neurodocker/reproenv/tests/test_renderers.py
neurodocker/reproenv/tests/test_renderers_docker.py
neurodocker/reproenv/tests/test_renderers_singularity.py
neurodocker/reproenv/tests/test_state.py
neurodocker/reproenv/tests/test_template.py
neurodocker/reproenv/tests/utils.py
neurodocker/templates/_default.yaml
neurodocker/templates/afni.yaml
neurodocker/templates/ants.yaml
neurodocker/templates/bids_validator.yaml
neurodocker/templates/cat12.yaml
neurodocker/templates/convert3d.yaml
neurodocker/templates/dcm2niix.yaml
neurodocker/templates/freesurfer.yaml
neurodocker/templates/fsl.yaml
neurodocker/templates/jq.yaml
neurodocker/templates/matlabmcr.yaml
neurodocker/templates/minc.yaml
neurodocker/templates/miniconda.yaml
neurodocker/templates/mricron.yaml
neurodocker/templates/mrtrix3.yaml
neurodocker/templates/ndfreeze.yaml
neurodocker/templates/neurodebian.yaml
neurodocker/templates/niftyreg.yaml
neurodocker/templates/petpvc.yaml
neurodocker/templates/spm12.yaml
neurodocker/templates/vnc.yaml
neurodocker-2.0.2.dist-info/METADATA
neurodocker-2.0.2.dist-info/WHEEL
neurodocker-2.0.2.dist-info/entry_points.txt
neurodocker-2.0.2.dist-info/licenses/LICENSE
neurodocker-2.0.2.dist-info/RECORD
