Metadata-Version: 2.4
Name: neurodocker
Version: 2.0.2
Summary: A generic generator of Dockerfiles and Singularity recipes.
Project-URL: Development, https://github.com/repronim/neurodocker
Project-URL: Homepage, https://www.repronim.org/neurodocker/
Author: Neurodocker Developers
Maintainer-email: Jakub Kaczmarzyk <jakub.kaczmarzyk@gmail.com>
License: Apache License, 2.0
License-File: LICENSE
Classifier: Development Status :: 4 - Beta
Classifier: Environment :: Console
Classifier: Intended Audience :: Developers
Classifier: Intended Audience :: Science/Research
Classifier: License :: OSI Approved :: Apache Software License
Classifier: Operating System :: OS Independent
Classifier: Programming Language :: Python :: 3
Classifier: Programming Language :: Python :: 3 :: Only
Classifier: Programming Language :: Python :: 3.9
Classifier: Programming Language :: Python :: 3.10
Classifier: Programming Language :: Python :: 3.11
Classifier: Programming Language :: Python :: 3.12
Classifier: Programming Language :: Python :: 3.13
Classifier: Topic :: Software Development
Classifier: Topic :: Software Development :: Libraries :: Python Modules
Requires-Python: >=3.9
Requires-Dist: click
Requires-Dist: etelemetry>=0.2.0
Requires-Dist: jinja2>=2.0
Requires-Dist: jsonschema>=3.0
Requires-Dist: mypy-extensions
Requires-Dist: pyyaml>=5.0
Requires-Dist: typing-extensions
Provides-Extra: all
Requires-Dist: codecov; extra == 'all'
Requires-Dist: coverage[toml]; extra == 'all'
Requires-Dist: docker>=4.4.1; extra == 'all'
Requires-Dist: pre-commit; extra == 'all'
Requires-Dist: pydata-sphinx-theme>=0.13; extra == 'all'
Requires-Dist: pytest-cov>=2.0.0; extra == 'all'
Requires-Dist: pytest-reportlog>=0.1.2; extra == 'all'
Requires-Dist: pytest-xdist>=2.2.0; extra == 'all'
Requires-Dist: pytest>=6.0; extra == 'all'
Requires-Dist: sphinx<7; extra == 'all'
Requires-Dist: sphinxcontrib-apidoc>=0.3; extra == 'all'
Provides-Extra: dev
Requires-Dist: codecov; extra == 'dev'
Requires-Dist: coverage[toml]; extra == 'dev'
Requires-Dist: docker>=4.4.1; extra == 'dev'
Requires-Dist: pre-commit; extra == 'dev'
Requires-Dist: pytest-cov>=2.0.0; extra == 'dev'
Requires-Dist: pytest-reportlog>=0.1.2; extra == 'dev'
Requires-Dist: pytest-xdist>=2.2.0; extra == 'dev'
Requires-Dist: pytest>=6.0; extra == 'dev'
Provides-Extra: doc
Requires-Dist: pydata-sphinx-theme>=0.13; extra == 'doc'
Requires-Dist: sphinx<7; extra == 'doc'
Requires-Dist: sphinxcontrib-apidoc>=0.3; extra == 'doc'
Provides-Extra: minify
Requires-Dist: docker>=4.4.1; extra == 'minify'
